Products.NoDuplicateLogin-2.0-py2.7-nspkg.pth
Products/NoDuplicateLogin/__init__.py
Products/NoDuplicateLogin/plugin.py
Products/NoDuplicateLogin/setuphandlers.py
Products/NoDuplicateLogin/tests.py
Products/NoDuplicateLogin/utils.py
Products/NoDuplicateLogin/views.py
Products.NoDuplicateLogin-2.0.dist-info/DESCRIPTION.rst
Products.NoDuplicateLogin-2.0.dist-info/entry_points.txt
Products.NoDuplicateLogin-2.0.dist-info/METADATA
Products.NoDuplicateLogin-2.0.dist-info/metadata.json
Products.NoDuplicateLogin-2.0.dist-info/namespace_packages.txt
Products.NoDuplicateLogin-2.0.dist-info/RECORD
Products.NoDuplicateLogin-2.0.dist-info/top_level.txt
Products.NoDuplicateLogin-2.0.dist-info/WHEEL
