Metadata-Version: 2.0
Name: Products.NoDuplicateLogin
Version: 2.0
Summary: Products.NoDuplicateLogin
Home-page: http://svn.plone.org/svn/collective/PASPlugins/Products.NoDuplicateLogin
Author: Daniel Nouri
Author-email: daniel.nouri@gmail.com
License: UNKNOWN
Platform: UNKNOWN
Requires-Dist: setuptools
Requires-Dist: collective.autopermission
Provides-Extra: tests
Requires-Dist: plone.app.testing; extra == 'tests'
